cmk_dev/bazelgraph.py
cmk_dev/devboard.py
cmk_dev/docker_randomized_port.py
cmk_dev/my_issues-backup.py
cmk_dev/gerrit_utils/client.py
cmk_dev/jira_utils/client.py
cmk_dev_tools-0.1.0.dist-info/METADATA
cmk_dev_tools-0.1.0.dist-info/WHEEL
cmk_dev_tools-0.1.0.dist-info/entry_points.txt
cmk_dev_tools-0.1.0.dist-info/RECORD
