Metadata-Version: 2.4
Name: cmk-dev-tools
Version: 0.1.0
Summary: Checkmk Dev Tools
Author-email: Benedikt Seidl <benedikt.seidl@checkmk.com>, Frans Fürst <frans.fuerst@checkmk.com>
Requires-Python: <4,>=3.10.4
Requires-Dist: aiohttp>=3.12.15
Requires-Dist: pydantic>=2
Requires-Dist: python-jenkins>=1.8.3
Requires-Dist: rich
Requires-Dist: textual>=6.6.0
Requires-Dist: trickkiste>=0.3.4
